RTL/combinational.v
module combinational (
    input a,
    input b,
    input c,
    input d,
    output y
);

assign y = (a & b) | (c & d);

endmodule

RTL/combinational_tb.v
module tb;

reg a;
reg b;
reg c;
reg d;
wire y;

combinational uut (
    .a(a),
    .b(b),
    .c(c),
    .d(d),
    .y(y)
);

initial begin 
    a <= 1'b0; b <= 1'b0; c <= 1'b0; d <= 1'b0;

    $dumpfile("combinational_tb.vcd");
    $dumpvars(0, tb);

    for (integer i = 0; i < 16; i = i + 1) begin
        {a, b, c, d} <= i;
        #5;
    end
end
endmodule

RTL/combinational_tb.vcd
$date
	Fri Aug  7 05:51:03 2026
$end
$version
	Icarus Verilog
$end
$timescale
	1s
$end
$scope module tb $end
$var wire 1 ! y $end
$var reg 1 " a $end
$var reg 1 # b $end
$var reg 1 $ c $end
$var reg 1 % d $end
$scope module uut $end
$var wire 1 " a $end
$var wire 1 # b $end
$var wire 1 $ c $end
$var wire 1 % d $end
$var wire 1 ! y $end
$upscope $end
$scope begin $ivl_for_loop0 $end
$var integer 32 & i [31:0] $end
$upscope $end
$upscope $end
$enddefinitions $end
$comment Show the parameter values. $end
$dumpall
$end
#0
$dumpvars
b0 &
0%
0$
0#
0"
0!
$end
#5
1%
b1 &
#10
1$
0%
b10 &
#15
1!
1%
b11 &
#20
0!
1#
0$
0%
b100 &
#25
1%
b101 &
#30
1$
0%
b110 &
#35
1!
1%
b111 &
#40
0!
1"
0#
0$
0%
b1000 &
#45
1%
b1001 &
#50
1$
0%
b1010 &
#55
1!
1%
b1011 &
#60
1#
0$
0%
b1100 &
#65
1%
b1101 &
#70
1$
0%
b1110 &
#75
1%
b1111 &
#80
b10000 &
