carrylookaheadadder.v
module cla_4bit (
    input  [3:0] a,
    input  [3:0] b,
    input        cin,
    output [3:0] sum,
    output       cout
);

wire [3:0] p;
wire [3:0] g;
wire [4:0] c;

// Propagate and Generate
assign p = a ^ b;
assign g = a & b;

// Carry Look-Ahead equations
assign c[0] = cin;

assign c[1] = g[0] | (p[0] & c[0]);

assign c[2] = g[1] |
             (p[1] & g[0]) |
             (p[1] & p[0] & c[0]);

assign c[3] = g[2] |
             (p[2] & g[1]) |
             (p[2] & p[1] & g[0]) |
             (p[2] & p[1] & p[0] & c[0]);

assign c[4] = g[3] |
             (p[3] & g[2]) |
             (p[3] & p[2] & g[1]) |
             (p[3] & p[2] & p[1] & g[0]) |
             (p[3] & p[2] & p[1] & p[0] & c[0]);

// Sum
assign sum = p ^ c[3:0];

// Final carry
assign cout = c[4];

endmodule

cla_b.v
module tb;

reg [3:0] a;
reg [3:0] b;
reg cin;
wire [3:0] sum;
wire cout;

integer i;

cla_4bit uut (
    .a(a),
    .b(b),
    .cin(cin),
    .sum(sum),
    .cout(cout)
);

initial begin 
    a <= 0;
    b <= 0;
    cin <= 0;

    $dumpfile("cla_tb.vcd");
    $dumpvars(0,tb);

    for (i=0; i<10; i=i+1) begin
        {a,b,cin} <= $random;
        #5;
    end

end
endmodule

cla_tb.vcd
$date
	Sat Aug  8 09:06:24 2026
$end
$version
	Icarus Verilog
$end
$timescale
	1s
$end
$scope module tb $end
$var wire 4 ! sum [3:0] $end
$var wire 1 " cout $end
$var reg 4 # a [3:0] $end
$var reg 4 $ b [3:0] $end
$var reg 1 % cin $end
$var integer 32 & i [31:0] $end
$scope module uut $end
$var wire 4 ' a [3:0] $end
$var wire 4 ( b [3:0] $end
$var wire 1 % cin $end
$var wire 4 ) g [3:0] $end
$var wire 4 * p [3:0] $end
$var wire 4 + sum [3:0] $end
$var wire 1 " cout $end
$var wire 5 , c [4:0] $end
$upscope $end
$upscope $end
$enddefinitions $end
$comment Show the parameter values. $end
$dumpall
$end
#0
$dumpvars
b0 ,
b1011 +
b1011 *
b0 )
b10 (
b1001 '
b0 &
0%
b10 $
b1001 #
0"
b1011 !
$end
#5
b101 !
b101 +
b100 *
b100 #
b100 '
b0 $
b0 (
b1 ,
1%
b1 &
#10
b0 #
b0 '
b100 $
b100 (
b10 &
#15
b111 ,
b101 !
b101 +
b10 *
b1 )
b11 #
b11 '
b1 $
b1 (
b11 &
#20
b1 ,
b1111 !
b1111 +
b1110 *
b0 )
b1000 #
b1000 '
b110 $
b110 (
b100 &
#25
1"
b11001 ,
b11 !
b11 +
b1010 *
b100 )
b1100 #
b1100 '
b101 &
#30
0"
b111 ,
b110 !
b110 +
b1 *
b10 )
b11 #
b11 '
b10 $
b10 (
b110 &
#35
b1001 !
b1001 +
b1001 *
b0 )
b0 #
b0 '
b1001 $
b1001 (
b0 ,
0%
b111 &
#40
b1001 !
b1001 +
b1000 *
b1000 #
b1000 '
b0 $
b0 (
b1 ,
1%
b1000 &
#45
b1111 !
b1111 +
b1110 *
b110 $
b110 (
b1001 &
#50
b1010 &
