RTL/half.v
module half(
    input a,
    input b,
    output sum,
    output c
);

assign sum = a^b;
assign c = a & b;

endmodule

half_tb.v
module tb;

reg a;
reg b;

wire sum;
wire c;

integer i;

half uut (
    .a(a),
    .b(b),
    .c(c),
    .sum(sum)
);

initial begin
    a <= 0;
    b <= 0;

    $dumpfile("half_tb.vcd");
    $dumpvars(0,tb);

    for (i = 0; i <10 ; i = i + 1) begin
        //{a,b} <= i;
        {a,b} <= $random; 
        #5;
    end
end
endmodule

half_tb.vcd
$date
	Tue Aug 11 02:31:48 2026
$end
$version
	Icarus Verilog
$end
$timescale
	1s
$end
$scope module tb $end
$var wire 1 ! sum $end
$var wire 1 " c $end
$var reg 1 # a $end
$var reg 1 $ b $end
$var integer 32 % i [31:0] $end
$scope module uut $end
$var wire 1 # a $end
$var wire 1 $ b $end
$var wire 1 " c $end
$var wire 1 ! sum $end
$upscope $end
$upscope $end
$enddefinitions $end
$comment Show the parameter values. $end
$dumpall
$end
#0
$dumpvars
b0 %
0$
0#
0"
0!
$end
#5
1!
1$
b1 %
#10
b10 %
#15
0!
1"
1#
b11 %
#20
1!
0"
0#
b100 %
#25
b101 %
#30
b110 %
#35
1#
0$
b111 %
#40
0#
1$
b1000 %
#45
b1001 %
#50
b1010 %
