alu.v
module alu (
    input [3:0] a,
    input [3:0] b,
    input [2:0] sel,
    output reg [3:0] result
);

always @(*) begin 
    if (sel==7) begin
        result <= 4'b0000;
    end
    else if (sel==6) begin
        result <= a >> 1;
    end
    else if (sel==5) begin 
        result <= a <<1;
    end
    else if (sel==4) begin
        result <= a^b;
    end
    else if (sel==3) begin 
        result <= a | b;
    end
    else if (sel==2) begin 
        result <= a & b;
    end
    else if (sel==1) begin 
        result <= a - b;
    end
    else begin
        result <= a + b;
    end
end
endmodule

alu_tb.v
module tb;

reg [3:0] a;
reg [3:0] b;
reg [2:0] sel;
wire [3:0] result;

integer i;

alu uut (
    .a(a),
    .b(b),
    .sel(sel),
    .result(result)
);

initial begin 
    a <= 4'b0101;
    b <= 0011;

    $dumpfile("alu_tb.vcd");
    $dumpvars(0,tb);

    for (i=0; i<8; i=i+1) begin 
        sel <= i;
        #5;
    end

    a <= 4'b1010;
    b <= 4'b0110;

    for (i=0; i<8; i=i+1) begin 
        sel <= i;
        #5;
    end

    a <= 4'b1111;
    b <= 4'b0001;

    for (i=0; i<8; i=i+1) begin 
        sel <= i;
        #5;
    end

end
endmodule

VCD/alu_tb.vcd
$date
	Sat Aug  8 03:59:03 2026
$end
$version
	Icarus Verilog
$end
$timescale
	1s
$end
$scope module tb $end
$var wire 4 ! result [3:0] $end
$var reg 4 " a [3:0] $end
$var reg 4 # b [3:0] $end
$var reg 3 $ sel [2:0] $end
$var integer 32 % i [31:0] $end
$scope module uut $end
$var wire 4 & a [3:0] $end
$var wire 4 ' b [3:0] $end
$var wire 3 ( sel [2:0] $end
$var reg 4 ) result [3:0] $end
$upscope $end
$upscope $end
$enddefinitions $end
$comment Show the parameter values. $end
$dumpall
$end
#0
$dumpvars
b0 )
b0 (
b1011 '
b101 &
b0 %
b0 $
b1011 #
b101 "
b0 !
$end
#5
b1010 !
b1010 )
b1 $
b1 (
b1 %
#10
b1 !
b1 )
b10 $
b10 (
b10 %
#15
b1111 !
b1111 )
b11 $
b11 (
b11 %
#20
b1110 !
b1110 )
b100 $
b100 (
b100 %
#25
b1010 !
b1010 )
b101 $
b101 (
b101 %
#30
b10 !
b10 )
b110 $
b110 (
b110 %
#35
b0 !
b0 )
b111 $
b111 (
b111 %
#40
b0 $
b0 (
b110 #
b110 '
b1010 "
b1010 &
b0 %
#45
b100 !
b100 )
b1 $
b1 (
b1 %
#50
b10 !
b10 )
b10 $
b10 (
b10 %
#55
b1110 !
b1110 )
b11 $
b11 (
b11 %
#60
b1100 !
b1100 )
b100 $
b100 (
b100 %
#65
b100 !
b100 )
b101 $
b101 (
b101 %
#70
b101 !
b101 )
b110 $
b110 (
b110 %
#75
b0 !
b0 )
b111 $
b111 (
b111 %
#80
b0 $
b0 (
b1 #
b1 '
b1111 "
b1111 &
b0 %
#85
b1110 !
b1110 )
b1 $
b1 (
b1 %
#90
b1 !
b1 )
b10 $
b10 (
b10 %
#95
b1111 !
b1111 )
b11 $
b11 (
b11 %
#100
b1110 !
b1110 )
b100 $
b100 (
b100 %
#105
b101 $
b101 (
b101 %
#110
b111 !
b111 )
b110 $
b110 (
b110 %
#115
b0 !
b0 )
b111 $
b111 (
b111 %
#120
b1000 %
