RTL/jk1.v
module jkff1 (
    input clk,
    input rst_n,
    input j,
    input k,
    output reg q
);

always @ (posedge clk or negedge rst_n) begin 
    if (!rst_n) begin 
        q <= 0;
    end
    else if (!j && !k) begin
        q <= q;
    end
    else if (j && !k) begin
        q <= 1;
    end
    else if (!j && k) begin
        q <= 0;
    end
    else if (j && k) begin
        q <= ~q;
    end
end
endmodule

jk1_tb.v
module tb;

reg clk;
reg rst_n;
reg j;
reg k;

wire q;

integer i;

jkff1 uut(
    .clk(clk),
    .rst_n(rst_n),
    .j(j),
    .k(k),
    .q(q)
);

initial begin 
    clk <= 0;
end

always #5 clk <= ~clk;

initial begin 
    j <= 0;
    k <= 0;
    rst_n <= 0;

    $dumpfile("jk1tb.vcd");
    $dumpvars(0,tb);

    #10 rst_n <= 1;

    for (i=0; i<4; i=i+1) begin
        {j,k} <= i;
        #10;
    end
    $finish;
end
endmodule

VCD/jk.vcd
$date
	Sun Aug  9 10:46:04 2026
$end
$version
	Icarus Verilog
$end
$timescale
	1s
$end
$scope module tb $end
$var wire 1 ! q $end
$var reg 1 " clk $end
$var reg 1 # j $end
$var reg 1 $ k $end
$var reg 1 % rst_n $end
$var integer 32 & i [31:0] $end
$scope module uut $end
$var wire 1 " clk $end
$var wire 1 # j $end
$var wire 1 $ k $end
$var wire 1 % rst_n $end
$var reg 1 ! q $end
$upscope $end
$upscope $end
$enddefinitions $end
$comment Show the parameter values. $end
$dumpall
$end
#0
$dumpvars
bx &
0%
0$
0#
0"
x!
$end
#5
0!
1"
#10
0"
1%
#15
1"
#20
0"
#25
1"
#30
0"
#35
1"
#40
0"
#45
1"
0%
b0 &
#50
0"
#55
1"
1$
b1 &
#60
0"
#65
1"
1#
0$
b10 &
#70
0"
#75
1"
1$
b11 &
#80
0"
#85
1"
b100 &
