priority_encoder.v
module pe (
    input [3:0] req,
    output reg [1:0] grant,
    output reg valid
);

always @(*) begin 
    valid = 1'b1;
    if (req[3]) 
        grant = 2'b11;
    else if (req[2])  
        grant = 2'b10;
    else if (req[1]) 
        grant = 2'b01;
    else if (req[0])  
        grant = 2'b00;
    else begin
        grant = 2'b00;
        valid = 1'b0;
    end
end
endmodule

RTL/priority_encoder_tb.v
module tb;

reg [3:0] req;
wire valid;
wire [1:0] grant;
integer i;

pe uut (
    .req(req),
    .valid(valid),
    .grant(grant)
);

initial begin 
    req = 4'b0000;
    $dumpfile("pe_tb.vcd");
    $dumpvars(0,tb);

    for (i=0; i<16; i=i+1) begin
        req = i;
        #5;
    end
end
endmodule

VCD/pe_tb.vcd
$date
	Sat Aug  8 03:41:37 2026
$end
$version
	Icarus Verilog
$end
$timescale
	1s
$end
$scope module tb $end
$var wire 1 ! valid $end
$var wire 2 " grant [1:0] $end
$var reg 4 # req [3:0] $end
$var integer 32 $ i [31:0] $end
$scope module uut $end
$var wire 4 % req [3:0] $end
$var reg 2 & grant [1:0] $end
$var reg 1 ! valid $end
$upscope $end
$upscope $end
$enddefinitions $end
$comment Show the parameter values. $end
$dumpall
$end
#0
$dumpvars
b0 &
b0 %
b0 $
b0 #
b0 "
0!
$end
#5
1!
b1 #
b1 %
b1 $
#10
b1 "
b1 &
b10 #
b10 %
b10 $
#15
b11 #
b11 %
b11 $
#20
b10 "
b10 &
b100 #
b100 %
b100 $
#25
b101 #
b101 %
b101 $
#30
b110 #
b110 %
b110 $
#35
b111 #
b111 %
b111 $
#40
b11 "
b11 &
b1000 #
b1000 %
b1000 $
#45
b1001 #
b1001 %
b1001 $
#50
b1010 #
b1010 %
b1010 $
#55
b1011 #
b1011 %
b1011 $
#60
b1100 #
b1100 %
b1100 $
#65
b1101 #
b1101 %
b1101 $
#70
b1110 #
b1110 %
b1110 $
#75
b1111 #
b1111 %
b1111 $
#80
b10000 $
